<?xml version="1.0" encoding="UTF-8" standalone="no"?><Hero><Name>庞统</Name><Title>凤雏</Title><Id>SHU010</Id><Pack>火</Pack><MaxLifePoints>0</MaxLifePoints><IsMonarch>false</IsMonarch><IsDivine>false</IsDivine><Gender>男</Gender><Faction>蜀</Faction><Abilities><Ability><AbilityName>连环</AbilityName><AbilityDescription>你可以将一张梅花手牌当【铁索连环】使用或重铸。</AbilityDescription><IsMonarchAbility>false</IsMonarchAbility><IsPassiveAbility>false</IsPassiveAbility><IsOneTimeAbility>false</IsOneTimeAbility></Ability><Ability><AbilityName>涅槃</AbilityName><AbilityDescription>限定技，当你处于濒死状态时，你可以弃置你区域里所有的牌，然后将你的武将牌恢复至游戏开始时的状态，再摸三张牌，最后回复至3点体力。</AbilityDescription><IsMonarchAbility>false</IsMonarchAbility><IsPassiveAbility>false</IsPassiveAbility><IsOneTimeAbility>true</IsOneTimeAbility></Ability></Abilities><AdditionalInfoForAbilities>
★庞统做主公时，发动涅槃后也只将体力回复至3点。</AdditionalInfoForAbilities><FAQs><Pair><Question>[Q]庞统濒死时，能否先求【桃】，没人给桃后再发动涅槃？
</Question><Answer>[A]从当前回合人开始依次结算，若庞统之前没人使用【桃】，则轮到庞统时须选择是否发动涅槃：若不发动，庞统之后的角色都不使用【桃】，庞统则不能再选择发动涅槃。

</Answer></Pair><Pair><Question>[Q]庞统在受到超过1点伤害后进入濒死状态时，发动涅槃回复几点体力？
</Question><Answer>[A]无论庞统濒死前受到几点伤害，进入濒死状态时发动涅槃，都将体力回复到3点。

</Answer></Pair><Pair><Question>[Q]庞统装备【白银狮子】时进入濒死状态发动涅槃，回复几点体力？
</Question><Answer>[A]回复至3点。涅槃已经发动，按其结算顺序结算：丢弃庞统所有的牌和判定区里的牌，这时丢弃【白银狮子】，庞统回复1点体力（尽管此时可能会濒死状态，但由于涅槃已经发动，应结算完毕），重置武将牌，然后摸三张牌并将体力回复至3点。

</Answer></Pair><Pair><Question>[Q]庞统的判定阶段依次判定【乐不思蜀】，【兵粮寸断】以及【闪电】，前两者都判中的情况下，被【闪电】击中进入濒死，庞统选择涅槃，此时庞统是否还要受到【乐不思蜀】及【兵粮寸断】的影响？
</Question><Answer>[A]受影响，依然需要跳过摸牌及出牌阶段。（另一种情况：若【闪电】是判定区里应最先判定的延时类锦囊，庞统被【闪电】击中进入濒死发动涅槃，则弃掉判定区里另外两张牌，不再进行判定。）

</Answer></Pair><Pair><Question>[Q]庞统发动涅槃能否重新选择武将？
</Question><Answer>[A]不能，重置武将牌的意思为解除连环状态，而非重新选择武将。

</Answer></Pair><Pair><Question>[Q]如果涅槃时被铁索连环，身份牌怎么放？
</Question><Answer>[A]重置回到未铁索连环的状态。

</Answer></Pair><Pair><Question>[Q]涅槃状态再次濒死可否求桃？
</Question><Answer>[A]可以。

</Answer></Pair><Pair><Question>[Q]如果庞统选择涅槃，其梦魇标记（神关羽的）是否取消掉？
</Question><Answer>[A]不取消，标记仍然保留。

</Answer></Pair><Pair><Question>[Q]如果庞统处于被神诸葛大雾或狂风技能影响状态后发动涅槃，大雾或者狂风状态是否取消？
</Question><Answer>[A]不取消，此两个技能状态依然保留。

</Answer></Pair><Pair><Question>[Q]如果庞统做主公，被天香后涅槃，是否可以摸因天香导致的牌？
</Question><Answer>[A]可以摸一张，因为庞统回复至3血后继续结算天香。</Answer></Pair></FAQs></Hero>